{"updated": "2026-07-20 12:24 UTC", "count": 300, "coins": [{"c": "OKB", "tf": {"1h": {"cur": 34672.71, "wk": 166163.93, "mo": null}, "4h": {"cur": 34286.73, "wk": 665214.13, "mo": 1101066.03}, "1d": {"cur": 1610441.53, "wk": 4045883.45, "mo": 6749536.43}}}, {"c": "SOL", "tf": {"1h": {"cur": 1843628.12, "wk": 1603588.85, "mo": null}, "4h": {"cur": 1843589.13, "wk": 6419601.18, "mo": 9817632.75}, "1d": {"cur": 30009417.52, "wk": 37627428.59, "mo": 58930989.18}}}, {"c": "DOGE", "tf": {"1h": {"cur": 477131.41, "wk": 685053.53, "mo": null}, "4h": {"cur": 477131.41, "wk": 2744392.01, "mo": 3414889.41}, "1d": {"cur": 9314913.43, "wk": 16650812.83, "mo": 20402912.84}}}, {"c": "HYPE", "tf": {"1h": {"cur": 305886.0, "wk": 1019040.93, "mo": null}, "4h": {"cur": 306133.37, "wk": 4068671.93, "mo": 5377871.95}, "1d": {"cur": 7799419.48, "wk": 24764466.49, "mo": 32484000.95}}}, {"c": "ZEC", "tf": {"1h": {"cur": 282173.14, "wk": 730184.07, "mo": null}, "4h": {"cur": 280686.7, "wk": 2922902.65, "mo": 2233483.67}, "1d": {"cur": 5817086.15, "wk": 18116815.59, "mo": 13511355.76}}}, {"c": "XRP", "tf": {"1h": {"cur": 719424.3, "wk": 715809.74, "mo": null}, "4h": {"cur": 719424.3, "wk": 2867678.01, "mo": 3487556.07}, "1d": {"cur": 9693313.19, "wk": 17314658.77, "mo": 20908861.65}}}, {"c": "SUI", "tf": {"1h": {"cur": 411106.36, "wk": 267781.47, "mo": null}, "4h": {"cur": 411106.36, "wk": 1072768.67, "mo": 1367912.61}, "1d": {"cur": 4837256.72, "wk": 6201925.12, "mo": 8149201.88}}}, {"c": "BCH", "tf": {"1h": {"cur": 44732.05, "wk": 94158.51, "mo": null}, "4h": {"cur": 44732.05, "wk": 376178.38, "mo": 389538.86}, "1d": {"cur": 830677.34, "wk": 2285296.51, "mo": 2343119.94}}}, {"c": "1INCH", "tf": {"1h": {"cur": 360.55, "wk": 1816.22, "mo": null}, "4h": {"cur": 360.55, "wk": 7273.9, "mo": 10910.51}, "1d": {"cur": 32577.08, "wk": 42594.32, "mo": 65614.66}}}, {"c": "2Z", "tf": {"1h": {"cur": 1726.13, "wk": 3276.97, "mo": null}, "4h": {"cur": 1726.13, "wk": 13098.08, "mo": 26419.96}, "1d": {"cur": 21735.5, "wk": 85195.57, "mo": 157706.05}}}, {"c": "A", "tf": {"1h": {"cur": 1813.08, "wk": 8948.96, "mo": null}, "4h": {"cur": 1813.08, "wk": 35881.27, "mo": 39164.29}, "1d": {"cur": 86284.2, "wk": 214104.17, "mo": 234624.87}}}, {"c": "AAVE", "tf": {"1h": {"cur": 37630.28, "wk": 78742.24, "mo": null}, "4h": {"cur": 37630.28, "wk": 315012.29, "mo": 502948.23}, "1d": {"cur": 737429.65, "wk": 1993080.4, "mo": 3018713.02}}}, {"c": "ACE", "tf": {"1h": {"cur": 99129.33, "wk": 18613.26, "mo": null}, "4h": {"cur": 99271.05, "wk": 77254.24, "mo": 29510.86}, "1d": {"cur": 2577538.29, "wk": 121651.72, "mo": 96403.74}}}, {"c": "ACH", "tf": {"1h": {"cur": 54.6, "wk": 1265.05, "mo": null}, "4h": {"cur": 54.6, "wk": 5051.56, "mo": 5231.95}, "1d": {"cur": 5180.96, "wk": 31881.93, "mo": 31344.12}}}, {"c": "ACT", "tf": {"1h": {"cur": 20486.9, "wk": 9775.3, "mo": null}, "4h": {"cur": 20601.21, "wk": 39197.1, "mo": 208213.08}, "1d": {"cur": 281857.01, "wk": 213205.04, "mo": 1207152.42}}}, {"c": "ADA", "tf": {"1h": {"cur": 99837.14, "wk": 196928.92, "mo": null}, "4h": {"cur": 99837.14, "wk": 788960.35, "mo": 901682.28}, "1d": {"cur": 3130283.5, "wk": 4605802.93, "mo": 5360307.03}}}, {"c": "AERGO", "tf": {"1h": {"cur": 5582.38, "wk": 10511.48, "mo": null}, "4h": {"cur": 5582.38, "wk": 41756.18, "mo": 29390.75}, "1d": {"cur": 74007.46, "wk": 249935.12, "mo": 170757.13}}}, {"c": "AEVO", "tf": {"1h": {"cur": 246.42, "wk": 886.63, "mo": null}, "4h": {"cur": 246.42, "wk": 3548.57, "mo": 9218.69}, "1d": {"cur": 14966.86, "wk": 19803.3, "mo": 54475.35}}}, {"c": "AGLD", "tf": {"1h": {"cur": 1073.11, "wk": 18619.26, "mo": null}, "4h": {"cur": 1073.11, "wk": 74084.75, "mo": 147510.74}, "1d": {"cur": 155393.72, "wk": 462307.34, "mo": 883319.93}}}, {"c": "AI", "tf": {"1h": {"cur": 18640.85, "wk": 56656.9, "mo": null}, "4h": {"cur": 18640.85, "wk": 226434.98, "mo": 328398.36}, "1d": {"cur": 391292.49, "wk": 1386535.82, "mo": 1965134.71}}}, {"c": "AIXBT", "tf": {"1h": {"cur": 2074.24, "wk": 2744.33, "mo": null}, "4h": {"cur": 2074.24, "wk": 10974.28, "mo": 13042.16}, "1d": {"cur": 35052.78, "wk": 64490.09, "mo": 77575.14}}}, {"c": "ALGO", "tf": {"1h": {"cur": 1404.83, "wk": 8020.72, "mo": null}, "4h": {"cur": 1404.83, "wk": 32064.0, "mo": 43830.68}, "1d": {"cur": 133676.04, "wk": 186156.11, "mo": 262000.24}}}, {"c": "ALLO", "tf": {"1h": {"cur": 36579.84, "wk": 197306.93, "mo": null}, "4h": {"cur": 36579.84, "wk": 793060.18, "mo": 629859.39}, "1d": {"cur": 1231080.83, "wk": 4710872.31, "mo": 3775913.13}}}, {"c": "ANIME", "tf": {"1h": {"cur": 89.78, "wk": 1645.44, "mo": null}, "4h": {"cur": 89.78, "wk": 6569.45, "mo": 19283.17}, "1d": {"cur": 24753.72, "wk": 39256.26, "mo": 139733.51}}}, {"c": "APE", "tf": {"1h": {"cur": 8881.26, "wk": 17958.29, "mo": null}, "4h": {"cur": 8881.26, "wk": 71820.61, "mo": 123685.02}, "1d": {"cur": 206719.58, "wk": 434131.81, "mo": 765292.88}}}, {"c": "API3", "tf": {"1h": {"cur": 316.8, "wk": 2217.05, "mo": null}, "4h": {"cur": 316.8, "wk": 8874.93, "mo": 12190.65}, "1d": {"cur": 34869.93, "wk": 53973.13, "mo": 73313.39}}}, {"c": "APT", "tf": {"1h": {"cur": 12229.59, "wk": 33648.78, "mo": null}, "4h": {"cur": 12229.59, "wk": 134765.02, "mo": 141843.21}, "1d": {"cur": 389574.5, "wk": 835832.35, "mo": 847860.5}}}, {"c": "AR", "tf": {"1h": {"cur": 1836.85, "wk": 12072.42, "mo": null}, "4h": {"cur": 1836.85, "wk": 48294.91, "mo": 66589.57}, "1d": {"cur": 192803.12, "wk": 289844.63, "mo": 397904.44}}}, {"c": "ARB", "tf": {"1h": {"cur": 31121.1, "wk": 51760.02, "mo": null}, "4h": {"cur": 57144.49, "wk": 206794.61, "mo": 238858.7}, "1d": {"cur": 530758.12, "wk": 1306469.07, "mo": 1420322.25}}}, {"c": "ARG", "tf": {"1h": {"cur": 11621.4, "wk": 46301.92, "mo": null}, "4h": {"cur": 11621.4, "wk": 186274.52, "mo": 51481.4}, "1d": {"cur": 635419.58, "wk": 968914.35, "mo": 274279.14}}}, {"c": "ARKM", "tf": {"1h": {"cur": 239.08, "wk": 3076.12, "mo": null}, "4h": {"cur": 239.08, "wk": 12298.44, "mo": 14279.71}, "1d": {"cur": 17424.54, "wk": 74625.79, "mo": 87992.61}}}, {"c": "ASP", "tf": {"1h": {"cur": 3648.51, "wk": 9550.81, "mo": null}, "4h": {"cur": 3648.51, "wk": 38825.01, "mo": 15967.05}, "1d": {"cur": 30835.36, "wk": 222669.86, "mo": 88893.67}}}, {"c": "ASTR", "tf": {"1h": {"cur": 2.17, "wk": 152.07, "mo": null}, "4h": {"cur": 2.17, "wk": 607.74, "mo": 1720.97}, "1d": {"cur": 1565.1, "wk": 3933.56, "mo": 14217.24}}}, {"c": "ASTER", "tf": {"1h": {"cur": 2170.08, "wk": 13775.63, "mo": null}, "4h": {"cur": 2170.08, "wk": 55139.11, "mo": 108941.5}, "1d": {"cur": 65301.14, "wk": 353491.97, "mo": 692785.42}}}, {"c": "ATH", "tf": {"1h": {"cur": 3305.9, "wk": 17805.16, "mo": null}, "4h": {"cur": 3305.9, "wk": 71069.42, "mo": 47138.51}, "1d": {"cur": 677456.21, "wk": 346878.82, "mo": 263978.09}}}, {"c": "ATOM", "tf": {"1h": {"cur": 6687.56, "wk": 10973.45, "mo": null}, "4h": {"cur": 6687.56, "wk": 43912.51, "mo": 57803.33}, "1d": {"cur": 185054.93, "wk": 260973.7, "mo": 343402.65}}}, {"c": "AUCTION", "tf": {"1h": {"cur": 26.35, "wk": 1003.32, "mo": null}, "4h": {"cur": 26.35, "wk": 4014.59, "mo": 11828.14}, "1d": {"cur": 11416.16, "wk": 24338.98, "mo": 70504.15}}}, {"c": "AUDM", "tf": {"1h": {"cur": 0.0, "wk": 534.54, "mo": null}, "4h": {"cur": 0.0, "wk": 2138.17, "mo": 4245.86}, "1d": {"cur": 0.0, "wk": 19307.24, "mo": 25489.69}}}, {"c": "AUDF", "tf": {"1h": {"cur": 0.0, "wk": 0.0, "mo": null}, "4h": {"cur": 0.0, "wk": 0.0, "mo": 0.0}, "1d": {"cur": 0.0, "wk": 0.0, "mo": 0.0}}}, {"c": "AVAX", "tf": {"1h": {"cur": 32730.11, "wk": 76474.99, "mo": null}, "4h": {"cur": 32730.11, "wk": 306209.57, "mo": 355009.47}, "1d": {"cur": 1378879.96, "wk": 1874315.4, "mo": 2170905.48}}}, {"c": "AVNT", "tf": {"1h": {"cur": 8376.97, "wk": 11104.72, "mo": null}, "4h": {"cur": 8376.97, "wk": 44407.05, "mo": 56625.63}, "1d": {"cur": 165404.59, "wk": 258321.6, "mo": 342984.74}}}, {"c": "AXS", "tf": {"1h": {"cur": 2470.73, "wk": 5403.96, "mo": null}, "4h": {"cur": 2470.73, "wk": 21611.43, "mo": 63085.87}, "1d": {"cur": 91151.28, "wk": 121391.66, "mo": 503565.55}}}, {"c": "BABYDOGE", "tf": {"1h": {"cur": 1.51, "wk": 2078.75, "mo": null}, "4h": {"cur": 1.51, "wk": 8321.42, "mo": 13152.95}, "1d": {"cur": 25459.53, "wk": 53609.89, "mo": 78923.78}}}, {"c": "BABY", "tf": {"1h": {"cur": 306.35, "wk": 5755.5, "mo": null}, "4h": {"cur": 306.35, "wk": 23003.32, "mo": 35124.25}, "1d": {"cur": 70864.84, "wk": 132847.77, "mo": 214201.6}}}, {"c": "BAND", "tf": {"1h": {"cur": 37.53, "wk": 611.71, "mo": null}, "4h": {"cur": 37.53, "wk": 2441.64, "mo": 3325.38}, "1d": {"cur": 2201.99, "wk": 14976.19, "mo": 20024.36}}}, {"c": "BANANA", "tf": {"1h": {"cur": 16.85, "wk": 753.74, "mo": null}, "4h": {"cur": 16.85, "wk": 3017.75, "mo": 9394.83}, "1d": {"cur": 14181.65, "wk": 18891.23, "mo": 54901.84}}}, {"c": "BARD", "tf": {"1h": {"cur": 42.09, "wk": 2563.06, "mo": null}, "4h": {"cur": 42.09, "wk": 10254.65, "mo": 10420.94}, "1d": {"cur": 35951.23, "wk": 60232.12, "mo": 62056.41}}}, {"c": "BASED", "tf": {"1h": {"cur": 40621.55, "wk": 101481.64, "mo": null}, "4h": {"cur": 40621.55, "wk": 405200.55, "mo": 706695.44}, "1d": {"cur": 765499.71, "wk": 2445629.64, "mo": 4373785.69}}}, {"c": "BAT", "tf": {"1h": {"cur": 714.79, "wk": 2566.12, "mo": null}, "4h": {"cur": 714.79, "wk": 10266.46, "mo": 13952.78}, "1d": {"cur": 46840.35, "wk": 57385.59, "mo": 84117.93}}}, {"c": "BERA", "tf": {"1h": {"cur": 8124.73, "wk": 9496.05, "mo": null}, "4h": {"cur": 8124.73, "wk": 37954.83, "mo": 48903.25}, "1d": {"cur": 581781.27, "wk": 160803.49, "mo": 281400.62}}}, {"c": "BETH", "tf": {"1h": {"cur": 6091.19, "wk": 13113.29, "mo": null}, "4h": {"cur": 6091.19, "wk": 52473.8, "mo": 50408.73}, "1d": {"cur": 159818.19, "wk": 329179.74, "mo": 299768.01}}}, {"c": "BICO", "tf": {"1h": {"cur": 640.92, "wk": 6454.85, "mo": null}, "4h": {"cur": 640.92, "wk": 25733.81, "mo": 200212.46}, "1d": {"cur": 59794.64, "wk": 151745.48, "mo": 1391972.34}}}, {"c": "BIGTIME", "tf": {"1h": {"cur": 12321.45, "wk": 3533.22, "mo": null}, "4h": {"cur": 12321.45, "wk": 14155.21, "mo": 15922.32}, "1d": {"cur": 72868.13, "wk": 82168.0, "mo": 94320.26}}}, {"c": "BIO", "tf": {"1h": {"cur": 4615.03, "wk": 6155.96, "mo": null}, "4h": {"cur": 4615.03, "wk": 24615.89, "mo": 62241.35}, "1d": {"cur": 84370.56, "wk": 155328.86, "mo": 382073.78}}}, {"c": "BLUR", "tf": {"1h": {"cur": 108.24, "wk": 13900.21, "mo": null}, "4h": {"cur": 108.24, "wk": 55486.81, "mo": 104781.23}, "1d": {"cur": 83125.35, "wk": 397662.27, "mo": 611525.12}}}, {"c": "BNB", "tf": {"1h": {"cur": 68778.59, "wk": 147377.64, "mo": null}, "4h": {"cur": 68778.59, "wk": 589897.63, "mo": 787311.33}, "1d": {"cur": 1856759.91, "wk": 3640675.32, "mo": 4735368.47}}}, {"c": "BNT", "tf": {"1h": {"cur": 17.74, "wk": 60.52, "mo": null}, "4h": {"cur": 17.74, "wk": 242.01, "mo": 369.82}, "1d": {"cur": 323.77, "wk": 1516.97, "mo": 2255.84}}}, {"c": "BOME", "tf": {"1h": {"cur": 99.37, "wk": 1754.09, "mo": null}, "4h": {"cur": 99.37, "wk": 7023.34, "mo": 12581.52}, "1d": {"cur": 61746.98, "wk": 37686.85, "mo": 75418.44}}}, {"c": "BONK", "tf": {"1h": {"cur": 149497.05, "wk": 69540.59, "mo": null}, "4h": {"cur": 149497.05, "wk": 278142.2, "mo": 249976.53}, "1d": {"cur": 1843958.84, "wk": 1450671.85, "mo": 1436517.25}}}, {"c": "BREV", "tf": {"1h": {"cur": 111.44, "wk": 4830.78, "mo": null}, "4h": {"cur": 111.44, "wk": 19293.95, "mo": 95840.05}, "1d": {"cur": 21945.12, "wk": 119083.05, "mo": 558415.55}}}, {"c": "BRL1", "tf": {"1h": {"cur": 0.0, "wk": 1752.27, "mo": null}, "4h": {"cur": 0.0, "wk": 7011.88, "mo": 6776.64}, "1d": {"cur": 517.3, "wk": 44176.94, "mo": 40686.04}}}, {"c": "CARDS", "tf": {"1h": {"cur": 12125.2, "wk": 25352.7, "mo": null}, "4h": {"cur": 12125.2, "wk": 101154.36, "mo": null}, "1d": {"cur": 118767.59, "wk": 637605.52, "mo": null}}}, {"c": "CATI", "tf": {"1h": {"cur": 272.25, "wk": 2868.39, "mo": null}, "4h": {"cur": 272.25, "wk": 11477.18, "mo": 15456.61}, "1d": {"cur": 13512.06, "wk": 69866.34, "mo": 94052.04}}}, {"c": "CAT", "tf": {"1h": {"cur": 420.88, "wk": 337.46, "mo": null}, "4h": {"cur": 420.88, "wk": 1350.29, "mo": 3016.96}, "1d": {"cur": 6243.38, "wk": 8558.29, "mo": 17969.42}}}, {"c": "CC", "tf": {"1h": {"cur": 1824.09, "wk": 39987.63, "mo": null}, "4h": {"cur": 1824.09, "wk": 159877.87, "mo": 158203.09}, "1d": {"cur": 223694.56, "wk": 950384.74, "mo": 949808.74}}}, {"c": "CELO", "tf": {"1h": {"cur": 3440.91, "wk": 6589.37, "mo": null}, "4h": {"cur": 3440.91, "wk": 26349.78, "mo": 53329.95}, "1d": {"cur": 76427.0, "wk": 162904.42, "mo": 325464.43}}}, {"c": "CELR", "tf": {"1h": {"cur": 0.65, "wk": 140.98, "mo": null}, "4h": {"cur": 0.65, "wk": 565.84, "mo": 630.58}, "1d": {"cur": 4851.34, "wk": 3387.14, "mo": 3696.71}}}, {"c": "CETUS", "tf": {"1h": {"cur": 40.41, "wk": 921.64, "mo": null}, "4h": {"cur": 40.41, "wk": 3688.41, "mo": 3072.02}, "1d": {"cur": 9329.07, "wk": 21494.77, "mo": 18289.31}}}, {"c": "CFG", "tf": {"1h": {"cur": 1573.24, "wk": 11863.34, "mo": null}, "4h": {"cur": 1573.24, "wk": 47543.7, "mo": 51205.32}, "1d": {"cur": 120758.94, "wk": 287949.58, "mo": 307710.28}}}, {"c": "CFX", "tf": {"1h": {"cur": 6235.53, "wk": 23940.34, "mo": null}, "4h": {"cur": 6235.53, "wk": 95848.34, "mo": 66314.61}, "1d": {"cur": 275497.69, "wk": 573946.1, "mo": 398381.39}}}, {"c": "CHIP", "tf": {"1h": {"cur": 2410.75, "wk": 5922.84, "mo": null}, "4h": {"cur": 2410.75, "wk": 23685.93, "mo": 65564.52}, "1d": {"cur": 74761.95, "wk": 143348.96, "mo": 391780.01}}}, {"c": "CHZ", "tf": {"1h": {"cur": 43086.76, "wk": 20628.71, "mo": null}, "4h": {"cur": 43086.76, "wk": 82734.09, "mo": 125579.46}, "1d": {"cur": 634127.53, "wk": 427150.75, "mo": 744600.47}}}, {"c": "CITY", "tf": {"1h": {"cur": 86.38, "wk": 235.51, "mo": null}, "4h": {"cur": 86.38, "wk": 942.78, "mo": 3298.04}, "1d": {"cur": 1019.75, "wk": 5758.05, "mo": 19557.04}}}, {"c": "COMP", "tf": {"1h": {"cur": 3169.78, "wk": 5887.98, "mo": null}, "4h": {"cur": 3169.78, "wk": 23545.61, "mo": 32530.35}, "1d": {"cur": 54105.78, "wk": 139637.27, "mo": 195063.51}}}, {"c": "CORE", "tf": {"1h": {"cur": 3165.37, "wk": 20463.95, "mo": null}, "4h": {"cur": 3165.37, "wk": 81894.79, "mo": 124213.95}, "1d": {"cur": 176649.53, "wk": 509364.54, "mo": 745521.04}}}, {"c": "CRO", "tf": {"1h": {"cur": 887.77, "wk": 55361.76, "mo": null}, "4h": {"cur": 887.77, "wk": 221383.97, "mo": 92735.29}, "1d": {"cur": 172095.95, "wk": 1350231.76, "mo": 558256.82}}}, {"c": "CRV", "tf": {"1h": {"cur": 6466.22, "wk": 27353.36, "mo": null}, "4h": {"cur": 6466.22, "wk": 109361.81, "mo": 95917.03}, "1d": {"cur": 413586.02, "wk": 638904.75, "mo": 570533.79}}}, {"c": "CSPR", "tf": {"1h": {"cur": 14063.23, "wk": 7527.64, "mo": null}, "4h": {"cur": 14927.57, "wk": 29982.77, "mo": 43350.17}, "1d": {"cur": 295991.39, "wk": 149823.49, "mo": 246093.75}}}, {"c": "CTC", "tf": {"1h": {"cur": 511.46, "wk": 908.37, "mo": null}, "4h": {"cur": 511.46, "wk": 3635.99, "mo": 6851.95}, "1d": {"cur": 8630.91, "wk": 24047.03, "mo": 40932.99}}}, {"c": "CVC", "tf": {"1h": {"cur": 11.18, "wk": 148.06, "mo": null}, "4h": {"cur": 11.18, "wk": 593.2, "mo": 2538.35}, "1d": {"cur": 5645.21, "wk": 3000.3, "mo": 15242.09}}}, {"c": "CVX", "tf": {"1h": {"cur": 1427.65, "wk": 2936.23, "mo": null}, "4h": {"cur": 1427.65, "wk": 11769.45, "mo": 6727.85}, "1d": {"cur": 17548.32, "wk": 70333.65, "mo": 39673.54}}}, {"c": "DASH", "tf": {"1h": {"cur": 9141.17, "wk": 15826.59, "mo": null}, "4h": {"cur": 9141.17, "wk": 63291.03, "mo": 76149.57}, "1d": {"cur": 158360.45, "wk": 380220.15, "mo": 457784.84}}}, {"c": "DEGEN", "tf": {"1h": {"cur": 514.34, "wk": 6756.39, "mo": null}, "4h": {"cur": 514.34, "wk": 26822.39, "mo": 20249.43}, "1d": {"cur": 50874.93, "wk": 143903.65, "mo": 119087.71}}}, {"c": "DGB", "tf": {"1h": {"cur": 1099.96, "wk": 6454.05, "mo": null}, "4h": {"cur": 1099.96, "wk": 25742.16, "mo": 6463.19}, "1d": {"cur": 39083.66, "wk": 151023.08, "mo": 37988.09}}}, {"c": "DOGS", "tf": {"1h": {"cur": 351.74, "wk": 1080.16, "mo": null}, "4h": {"cur": 351.74, "wk": 4319.69, "mo": 17332.74}, "1d": {"cur": 18794.07, "wk": 25811.71, "mo": 102800.03}}}, {"c": "DOOD", "tf": {"1h": {"cur": 39757.99, "wk": 20373.5, "mo": null}, "4h": {"cur": 39757.99, "wk": 81597.95, "mo": 77930.81}, "1d": {"cur": 560380.95, "wk": 422102.84, "mo": 448381.13}}}, {"c": "DORA", "tf": {"1h": {"cur": 2.0, "wk": 646.36, "mo": null}, "4h": {"cur": 2.0, "wk": 2586.95, "mo": 8210.94}, "1d": {"cur": 6646.35, "wk": 15688.38, "mo": 49162.2}}}, {"c": "DOT", "tf": {"1h": {"cur": 44616.7, "wk": 63020.72, "mo": null}, "4h": {"cur": 44622.3, "wk": 252238.19, "mo": 220262.98}, "1d": {"cur": 1130955.12, "wk": 1417353.07, "mo": 1295678.73}}}, {"c": "DUCK", "tf": {"1h": {"cur": 2892.44, "wk": 1016.99, "mo": null}, "4h": {"cur": 2892.44, "wk": 4031.05, "mo": 7271.61}, "1d": {"cur": 10103.67, "wk": 24863.8, "mo": 44122.59}}}, {"c": "DYDX", "tf": {"1h": {"cur": 1260.23, "wk": 18222.59, "mo": null}, "4h": {"cur": 1260.23, "wk": 72841.78, "mo": 254099.71}, "1d": {"cur": 87939.6, "wk": 467456.45, "mo": 1442535.32}}}, {"c": "EDGE", "tf": {"1h": {"cur": 6564.5, "wk": 59734.38, "mo": null}, "4h": {"cur": 6564.5, "wk": 239781.87, "mo": 362679.4}, "1d": {"cur": 427458.18, "wk": 1477569.87, "mo": 2140302.68}}}, {"c": "EGLD", "tf": {"1h": {"cur": 1262.87, "wk": 14309.95, "mo": null}, "4h": {"cur": 1262.87, "wk": 57089.09, "mo": 22071.83}, "1d": {"cur": 41297.0, "wk": 354131.94, "mo": 130774.01}}}, {"c": "EIGEN", "tf": {"1h": {"cur": 14863.19, "wk": 32074.24, "mo": null}, "4h": {"cur": 14863.19, "wk": 128204.88, "mo": 140112.76}, "1d": {"cur": 256195.31, "wk": 796488.26, "mo": 936806.32}}}, {"c": "ELF", "tf": {"1h": {"cur": 0.0, "wk": 2514.52, "mo": null}, "4h": {"cur": 0.0, "wk": 9846.64, "mo": 35797.96}, "1d": {"cur": 15136.43, "wk": 60231.95, "mo": 208293.09}}}, {"c": "ENA", "tf": {"1h": {"cur": 53289.45, "wk": 49356.29, "mo": null}, "4h": {"cur": 53289.45, "wk": 197378.58, "mo": 266430.47}, "1d": {"cur": 427176.63, "wk": 1233456.68, "mo": 1598752.31}}}, {"c": "ENJ", "tf": {"1h": {"cur": 76.92, "wk": 2467.13, "mo": null}, "4h": {"cur": 76.92, "wk": 9859.97, "mo": 17276.57}, "1d": {"cur": 22958.34, "wk": 60922.49, "mo": 110026.16}}}, {"c": "ENS", "tf": {"1h": {"cur": 26795.93, "wk": 21536.47, "mo": null}, "4h": {"cur": 26873.94, "wk": 86179.38, "mo": 47039.13}, "1d": {"cur": 262680.13, "wk": 493299.84, "mo": 306244.83}}}, {"c": "ETC", "tf": {"1h": {"cur": 6648.32, "wk": 26250.03, "mo": null}, "4h": {"cur": 6648.32, "wk": 105116.83, "mo": 121329.74}, "1d": {"cur": 670577.25, "wk": 619268.49, "mo": 721536.17}}}, {"c": "ETHW", "tf": {"1h": {"cur": 1124.76, "wk": 2734.83, "mo": null}, "4h": {"cur": 1124.76, "wk": 10935.65, "mo": 17133.22}, "1d": {"cur": 31067.0, "wk": 63528.71, "mo": 101619.0}}}, {"c": "ETHFI", "tf": {"1h": {"cur": 18766.94, "wk": 55004.23, "mo": null}, "4h": {"cur": 18766.94, "wk": 220527.78, "mo": 231633.87}, "1d": {"cur": 562088.77, "wk": 1346995.57, "mo": 1381032.75}}}, {"c": "FET", "tf": {"1h": {"cur": 14384.92, "wk": 16908.67, "mo": null}, "4h": {"cur": 14384.92, "wk": 67582.54, "mo": 91580.24}, "1d": {"cur": 523795.1, "wk": 367510.44, "mo": 539098.42}}}, {"c": "FIL", "tf": {"1h": {"cur": 29321.68, "wk": 116628.24, "mo": null}, "4h": {"cur": 29315.73, "wk": 466842.39, "mo": 634873.43}, "1d": {"cur": 1971748.46, "wk": 2717141.07, "mo": 3788291.11}}}, {"c": "FLOW", "tf": {"1h": {"cur": 39.39, "wk": 857.39, "mo": null}, "4h": {"cur": 39.39, "wk": 3430.07, "mo": 4921.75}, "1d": {"cur": 11828.03, "wk": 19231.54, "mo": 29719.06}}}, {"c": "FLOKI", "tf": {"1h": {"cur": 2119.44, "wk": 2944.3, "mo": null}, "4h": {"cur": 2119.44, "wk": 11779.51, "mo": 19351.08}, "1d": {"cur": 38030.47, "wk": 68927.73, "mo": 117336.97}}}, {"c": "FLR", "tf": {"1h": {"cur": 1400.54, "wk": 6899.6, "mo": null}, "4h": {"cur": 1400.54, "wk": 27531.58, "mo": 27947.39}, "1d": {"cur": 62725.11, "wk": 160842.14, "mo": 167100.28}}}, {"c": "FLUID", "tf": {"1h": {"cur": 2359.98, "wk": 1468.54, "mo": null}, "4h": {"cur": 2359.98, "wk": 5876.26, "mo": 15943.52}, "1d": {"cur": 30939.04, "wk": 33904.98, "mo": 96649.13}}}, {"c": "FOGO", "tf": {"1h": {"cur": 18601.42, "wk": 6094.13, "mo": null}, "4h": {"cur": 18601.42, "wk": 24390.77, "mo": 62511.5}, "1d": {"cur": 130219.22, "wk": 138861.45, "mo": 375213.69}}}, {"c": "G", "tf": {"1h": {"cur": 958.06, "wk": 9309.14, "mo": null}, "4h": {"cur": 958.06, "wk": 36031.66, "mo": 76195.94}, "1d": {"cur": 97824.51, "wk": 210994.35, "mo": 437316.9}}}, {"c": "GALA", "tf": {"1h": {"cur": 25195.21, "wk": 20508.93, "mo": null}, "4h": {"cur": 25195.21, "wk": 81927.75, "mo": 45338.85}, "1d": {"cur": 204951.52, "wk": 474425.56, "mo": 271289.14}}}, {"c": "GALFT", "tf": {"1h": {"cur": 197.31, "wk": 2094.38, "mo": null}, "4h": {"cur": 197.31, "wk": 8374.51, "mo": 4228.89}, "1d": {"cur": 47468.9, "wk": 50850.95, "mo": 24095.19}}}, {"c": "GAS", "tf": {"1h": {"cur": 2908.36, "wk": 9572.29, "mo": null}, "4h": {"cur": 2908.36, "wk": 38193.13, "mo": 48133.57}, "1d": {"cur": 226988.91, "wk": 206404.3, "mo": 279426.19}}}, {"c": "GLM", "tf": {"1h": {"cur": 522.86, "wk": 695.96, "mo": null}, "4h": {"cur": 522.86, "wk": 2781.49, "mo": 6572.04}, "1d": {"cur": 13218.83, "wk": 15079.19, "mo": 38586.21}}}, {"c": "GMT", "tf": {"1h": {"cur": 349.2, "wk": 1620.86, "mo": null}, "4h": {"cur": 349.2, "wk": 6479.34, "mo": 7339.05}, "1d": {"cur": 21758.41, "wk": 40232.2, "mo": 44112.84}}}, {"c": "GMX", "tf": {"1h": {"cur": 7.67, "wk": 1345.07, "mo": null}, "4h": {"cur": 7.67, "wk": 5396.12, "mo": 5788.28}, "1d": {"cur": 7724.33, "wk": 34713.35, "mo": 36019.81}}}, {"c": "GOAT", "tf": {"1h": {"cur": 3785.76, "wk": 1240.8, "mo": null}, "4h": {"cur": 3785.76, "wk": 4959.04, "mo": 12489.99}, "1d": {"cur": 49244.6, "wk": 24845.82, "mo": 72989.73}}}, {"c": "GODS", "tf": {"1h": {"cur": 13.28, "wk": 172.38, "mo": null}, "4h": {"cur": 13.28, "wk": 688.82, "mo": 8886.29}, "1d": {"cur": 2796.97, "wk": 4525.74, "mo": 47503.47}}}, {"c": "GRASS", "tf": {"1h": {"cur": 12962.28, "wk": 26728.82, "mo": null}, "4h": {"cur": 12962.28, "wk": 106717.63, "mo": 197303.23}, "1d": {"cur": 210718.43, "wk": 663321.96, "mo": 1175256.26}}}, {"c": "GRT", "tf": {"1h": {"cur": 3280.61, "wk": 3937.18, "mo": null}, "4h": {"cur": 3280.61, "wk": 15754.64, "mo": 14372.98}, "1d": {"cur": 80303.22, "wk": 94264.11, "mo": 86747.93}}}, {"c": "HBAR", "tf": {"1h": {"cur": 16500.17, "wk": 20666.24, "mo": null}, "4h": {"cur": 16500.17, "wk": 82774.97, "mo": 119761.71}, "1d": {"cur": 193027.29, "wk": 514030.84, "mo": 720613.64}}}, {"c": "HMSTR", "tf": {"1h": {"cur": 4335.68, "wk": 22883.53, "mo": null}, "4h": {"cur": 4335.68, "wk": 91437.66, "mo": 324675.74}, "1d": {"cur": 136329.19, "wk": 588111.47, "mo": 1932594.08}}}, {"c": "HUMA", "tf": {"1h": {"cur": 2363.65, "wk": 7316.41, "mo": null}, "4h": {"cur": 2363.65, "wk": 29273.82, "mo": 42061.66}, "1d": {"cur": 136140.06, "wk": 164309.54, "mo": 247434.82}}}, {"c": "ICP", "tf": {"1h": {"cur": 15137.15, "wk": 34625.57, "mo": null}, "4h": {"cur": 15137.15, "wk": 138606.37, "mo": 195978.64}, "1d": {"cur": 447287.56, "wk": 848484.42, "mo": 1186908.79}}}, {"c": "ICX", "tf": {"1h": {"cur": 654.34, "wk": 516.4, "mo": null}, "4h": {"cur": 654.34, "wk": 2066.92, "mo": 4019.76}, "1d": {"cur": 2759.55, "wk": 13070.54, "mo": 24058.26}}}, {"c": "ID", "tf": {"1h": {"cur": 2281.19, "wk": 2685.61, "mo": null}, "4h": {"cur": 2281.19, "wk": 10708.91, "mo": 59359.39}, "1d": {"cur": 55506.31, "wk": 65384.02, "mo": 354307.48}}}, {"c": "ILV", "tf": {"1h": {"cur": 71.92, "wk": 403.67, "mo": null}, "4h": {"cur": 71.92, "wk": 1614.27, "mo": 2871.59}, "1d": {"cur": 4235.88, "wk": 9499.0, "mo": 17282.98}}}, {"c": "IMX", "tf": {"1h": {"cur": 2980.25, "wk": 1708.99, "mo": null}, "4h": {"cur": 2980.25, "wk": 6826.84, "mo": 19107.74}, "1d": {"cur": 18781.34, "wk": 43864.39, "mo": 115632.21}}}, {"c": "INJ", "tf": {"1h": {"cur": 28716.71, "wk": 28566.96, "mo": null}, "4h": {"cur": 28716.71, "wk": 114291.78, "mo": 119164.37}, "1d": {"cur": 329416.09, "wk": 671734.31, "mo": 712080.82}}}, {"c": "IOST", "tf": {"1h": {"cur": 556.45, "wk": 1315.67, "mo": null}, "4h": {"cur": 556.45, "wk": 5267.54, "mo": 7467.75}, "1d": {"cur": 9103.77, "wk": 32235.87, "mo": 44353.19}}}, {"c": "IOTA", "tf": {"1h": {"cur": 4785.59, "wk": 16221.25, "mo": null}, "4h": {"cur": 4785.59, "wk": 64863.46, "mo": 99255.91}, "1d": {"cur": 175023.13, "wk": 399708.4, "mo": 589539.67}}}, {"c": "DATA", "tf": {"1h": {"cur": 20385.17, "wk": 112974.18, "mo": null}, "4h": {"cur": 20385.17, "wk": 448694.24, "mo": null}, "1d": {"cur": 460028.57, "wk": 2950846.24, "mo": null}}}, {"c": "IRYS", "tf": {"1h": {"cur": 7296.28, "wk": 9685.39, "mo": null}, "4h": {"cur": 7296.28, "wk": 38754.46, "mo": 61746.25}, "1d": {"cur": 119858.84, "wk": 254563.02, "mo": 368842.47}}}, {"c": "JITOSOL", "tf": {"1h": {"cur": 2.12, "wk": 690.2, "mo": null}, "4h": {"cur": 2.12, "wk": 2761.76, "mo": 5455.06}, "1d": {"cur": 1678.89, "wk": 16675.63, "mo": 33155.8}}}, {"c": "JOE", "tf": {"1h": {"cur": 0.65, "wk": 65.51, "mo": null}, "4h": {"cur": 0.65, "wk": 261.49, "mo": 490.46}, "1d": {"cur": 612.85, "wk": 1582.22, "mo": 2954.96}}}, {"c": "JTO", "tf": {"1h": {"cur": 22416.6, "wk": 53863.88, "mo": null}, "4h": {"cur": 22416.6, "wk": 214951.21, "mo": 427911.95}, "1d": {"cur": 1421587.34, "wk": 1320853.19, "mo": 2563776.03}}}, {"c": "JUP", "tf": {"1h": {"cur": 13827.01, "wk": 30645.94, "mo": null}, "4h": {"cur": 13827.01, "wk": 122556.6, "mo": 152167.03}, "1d": {"cur": 642613.95, "wk": 680079.45, "mo": 907587.72}}}, {"c": "KAIA", "tf": {"1h": {"cur": 3736.05, "wk": 9570.8, "mo": null}, "4h": {"cur": 3736.05, "wk": 38244.57, "mo": 25265.19}, "1d": {"cur": 111058.69, "wk": 217591.88, "mo": 149248.36}}}, {"c": "KAITO", "tf": {"1h": {"cur": 23180.87, "wk": 143938.6, "mo": null}, "4h": {"cur": 23180.87, "wk": 577911.34, "mo": 288257.12}, "1d": {"cur": 2286537.05, "wk": 3299752.31, "mo": 1656909.38}}}, {"c": "KAT", "tf": {"1h": {"cur": 7329.39, "wk": 23183.17, "mo": null}, "4h": {"cur": 7329.39, "wk": 93034.12, "mo": 95078.69}, "1d": {"cur": 231791.66, "wk": 581210.09, "mo": 599622.05}}}, {"c": "KITE", "tf": {"1h": {"cur": 14373.26, "wk": 42448.1, "mo": null}, "4h": {"cur": 14373.26, "wk": 169419.19, "mo": 98725.33}, "1d": {"cur": 605980.33, "wk": 1227128.16, "mo": 577897.19}}}, {"c": "KMNO", "tf": {"1h": {"cur": 69.89, "wk": 4126.79, "mo": null}, "4h": {"cur": 69.89, "wk": 16500.17, "mo": 35684.03}, "1d": {"cur": 30939.55, "wk": 106982.63, "mo": 217015.74}}}, {"c": "KNC", "tf": {"1h": {"cur": 435.03, "wk": 378.71, "mo": null}, "4h": {"cur": 435.03, "wk": 1495.86, "mo": 1203.9}, "1d": {"cur": 38680.52, "wk": 3488.71, "mo": 5900.8}}}, {"c": "KSM", "tf": {"1h": {"cur": 2350.25, "wk": 2431.42, "mo": null}, "4h": {"cur": 2350.25, "wk": 9731.32, "mo": 17069.79}, "1d": {"cur": 37956.13, "wk": 56432.34, "mo": 102935.44}}}, {"c": "LAT", "tf": {"1h": {"cur": 30.06, "wk": 22848.7, "mo": null}, "4h": {"cur": 30.06, "wk": 92130.91, "mo": 92139.15}, "1d": {"cur": 194290.2, "wk": 566778.74, "mo": 551551.09}}}, {"c": "LAYER", "tf": {"1h": {"cur": 854.36, "wk": 2218.59, "mo": null}, "4h": {"cur": 854.36, "wk": 8796.24, "mo": 64890.0}, "1d": {"cur": 42724.98, "wk": 48193.19, "mo": 368989.82}}}, {"c": "LDO", "tf": {"1h": {"cur": 14524.17, "wk": 47914.67, "mo": null}, "4h": {"cur": 14524.17, "wk": 191920.16, "mo": 134493.12}, "1d": {"cur": 233923.49, "wk": 1186033.1, "mo": 810540.03}}}, {"c": "LEO", "tf": {"1h": {"cur": 19.51, "wk": 330.94, "mo": null}, "4h": {"cur": 19.51, "wk": 1324.35, "mo": 8819.48}, "1d": {"cur": 3543.18, "wk": 10518.22, "mo": 52976.36}}}, {"c": "LINK", "tf": {"1h": {"cur": 207554.22, "wk": 95828.8, "mo": null}, "4h": {"cur": 207554.22, "wk": 383941.4, "mo": 400204.98}, "1d": {"cur": 1345609.5, "wk": 2318947.58, "mo": 2392500.05}}}, {"c": "LINEA", "tf": {"1h": {"cur": 3336.15, "wk": 8070.02, "mo": null}, "4h": {"cur": 3336.15, "wk": 32304.27, "mo": 27924.71}, "1d": {"cur": 60210.66, "wk": 196198.63, "mo": 167512.15}}}, {"c": "LIT", "tf": {"1h": {"cur": 26583.89, "wk": 232403.98, "mo": null}, "4h": {"cur": 26583.89, "wk": 928550.81, "mo": 1076045.51}, "1d": {"cur": 1471924.67, "wk": 5953304.07, "mo": 6451668.85}}}, {"c": "LPT", "tf": {"1h": {"cur": 3833.74, "wk": 2285.81, "mo": null}, "4h": {"cur": 3833.74, "wk": 9148.01, "mo": 13946.03}, "1d": {"cur": 68089.57, "wk": 50090.66, "mo": 82410.92}}}, {"c": "LQTY", "tf": {"1h": {"cur": 152.55, "wk": 904.35, "mo": null}, "4h": {"cur": 152.55, "wk": 3620.92, "mo": 9878.37}, "1d": {"cur": 13272.87, "wk": 21002.6, "mo": 59493.33}}}, {"c": "LRC", "tf": {"1h": {"cur": 9170.55, "wk": 40476.51, "mo": null}, "4h": {"cur": 9170.55, "wk": 163713.22, "mo": 49409.54}, "1d": {"cur": 276829.82, "wk": 961291.66, "mo": 284663.6}}}, {"c": "LSK", "tf": {"1h": {"cur": 735.67, "wk": 7423.36, "mo": null}, "4h": {"cur": 735.67, "wk": 29684.41, "mo": 36440.51}, "1d": {"cur": 56864.39, "wk": 179694.46, "mo": 218380.73}}}, {"c": "LTC", "tf": {"1h": {"cur": 244002.76, "wk": 217042.94, "mo": null}, "4h": {"cur": 244002.76, "wk": 868135.67, "mo": 721117.08}, "1d": {"cur": 3394111.6, "wk": 5011259.69, "mo": 4264228.18}}}, {"c": "LUNA", "tf": {"1h": {"cur": 371.27, "wk": 5659.94, "mo": null}, "4h": {"cur": 371.27, "wk": 22630.54, "mo": 21222.87}, "1d": {"cur": 28707.01, "wk": 136530.07, "mo": 127631.51}}}, {"c": "MAGIC", "tf": {"1h": {"cur": 6543.75, "wk": 3859.47, "mo": null}, "4h": {"cur": 6543.75, "wk": 15462.43, "mo": 31013.55}, "1d": {"cur": 201747.29, "wk": 68896.06, "mo": 177896.62}}}, {"c": "MANA", "tf": {"1h": {"cur": 4879.71, "wk": 10951.4, "mo": null}, "4h": {"cur": 4879.71, "wk": 43844.22, "mo": 44828.23}, "1d": {"cur": 178423.07, "wk": 256474.58, "mo": 275802.84}}}, {"c": "MASK", "tf": {"1h": {"cur": 1260.94, "wk": 2148.57, "mo": null}, "4h": {"cur": 1260.94, "wk": 8601.92, "mo": 14504.21}, "1d": {"cur": 44209.37, "wk": 52779.29, "mo": 95666.63}}}, {"c": "ME", "tf": {"1h": {"cur": 115.3, "wk": 3454.62, "mo": null}, "4h": {"cur": 115.3, "wk": 13814.48, "mo": 42178.85}, "1d": {"cur": 20042.09, "wk": 82377.99, "mo": 252415.25}}}, {"c": "MEGA", "tf": {"1h": {"cur": 5739.33, "wk": 18903.64, "mo": null}, "4h": {"cur": 5741.08, "wk": 75347.28, "mo": 105309.27}, "1d": {"cur": 219667.69, "wk": 449913.13, "mo": 650390.57}}}, {"c": "MEME", "tf": {"1h": {"cur": 1153.17, "wk": 5819.97, "mo": null}, "4h": {"cur": 1153.17, "wk": 23318.51, "mo": 29485.35}, "1d": {"cur": 55521.22, "wk": 140890.58, "mo": 180034.81}}}, {"c": "MENGO", "tf": {"1h": {"cur": 61.34, "wk": 3056.63, "mo": null}, "4h": {"cur": 61.34, "wk": 11955.51, "mo": 4116.12}, "1d": {"cur": 7109.46, "wk": 67332.11, "mo": 23732.26}}}, {"c": "MERL", "tf": {"1h": {"cur": 35874.12, "wk": 9765.69, "mo": null}, "4h": {"cur": 35874.12, "wk": 38987.16, "mo": 62855.99}, "1d": {"cur": 488111.24, "wk": 186448.05, "mo": 366145.35}}}, {"c": "METIS", "tf": {"1h": {"cur": 205.68, "wk": 955.41, "mo": null}, "4h": {"cur": 205.68, "wk": 3815.21, "mo": 7332.15}, "1d": {"cur": 4347.3, "wk": 24874.36, "mo": 48168.39}}}, {"c": "MET", "tf": {"1h": {"cur": 50718.88, "wk": 30221.66, "mo": null}, "4h": {"cur": 50718.88, "wk": 121265.57, "mo": 148750.94}, "1d": {"cur": 1279255.19, "wk": 577105.19, "mo": 902485.94}}}, {"c": "MEW", "tf": {"1h": {"cur": 4383.92, "wk": 7909.51, "mo": null}, "4h": {"cur": 4383.92, "wk": 31736.22, "mo": 21920.36}, "1d": {"cur": 68047.6, "wk": 182196.61, "mo": 130345.91}}}, {"c": "MINA", "tf": {"1h": {"cur": 2416.13, "wk": 4773.96, "mo": null}, "4h": {"cur": 2416.13, "wk": 19113.85, "mo": 24431.09}, "1d": {"cur": 48594.25, "wk": 114355.53, "mo": 147296.13}}}, {"c": "MMT", "tf": {"1h": {"cur": 860.68, "wk": 14929.97, "mo": null}, "4h": {"cur": 860.68, "wk": 59686.05, "mo": 82498.84}, "1d": {"cur": 205578.52, "wk": 340176.4, "mo": 487269.26}}}, {"c": "MON", "tf": {"1h": {"cur": 6091.16, "wk": 46222.23, "mo": null}, "4h": {"cur": 6091.16, "wk": 184188.44, "mo": 2960664.58}, "1d": {"cur": 551439.2, "wk": 1087322.74, "mo": 18229048.11}}}, {"c": "MOODENG", "tf": {"1h": {"cur": 113428.35, "wk": 21277.48, "mo": null}, "4h": {"cur": 112942.73, "wk": 85397.19, "mo": 86850.07}, "1d": {"cur": 367295.45, "wk": 487374.52, "mo": 511829.08}}}, {"c": "MORPHO", "tf": {"1h": {"cur": 807.27, "wk": 18750.71, "mo": null}, "4h": {"cur": 807.27, "wk": 74831.19, "mo": 96703.49}, "1d": {"cur": 80097.68, "wk": 485871.77, "mo": 579296.59}}}, {"c": "MOVE", "tf": {"1h": {"cur": 1664.38, "wk": 6061.89, "mo": null}, "4h": {"cur": 1664.38, "wk": 24269.26, "mo": 34863.84}, "1d": {"cur": 72602.26, "wk": 144438.36, "mo": 210973.28}}}, {"c": "NAVX", "tf": {"1h": {"cur": 10322.34, "wk": 4589.95, "mo": null}, "4h": {"cur": 10322.34, "wk": 18626.1, "mo": 8971.58}, "1d": {"cur": 366428.76, "wk": 60436.15, "mo": 41992.45}}}, {"c": "NEAR", "tf": {"1h": {"cur": 112042.08, "wk": 152623.43, "mo": null}, "4h": {"cur": 111981.73, "wk": 610995.61, "mo": 720762.12}, "1d": {"cur": 1359870.61, "wk": 3806897.56, "mo": 4316433.33}}}, {"c": "NEIRO", "tf": {"1h": {"cur": 532.88, "wk": 2700.56, "mo": null}, "4h": {"cur": 532.88, "wk": 10800.21, "mo": 20089.29}, "1d": {"cur": 43115.92, "wk": 66634.57, "mo": 120373.92}}}, {"c": "NEO", "tf": {"1h": {"cur": 1137.34, "wk": 9026.9, "mo": null}, "4h": {"cur": 1137.34, "wk": 36169.95, "mo": 19932.98}, "1d": {"cur": 115816.24, "wk": 203840.2, "mo": 116745.01}}}, {"c": "NES", "tf": {"1h": {"cur": 1290.98, "wk": 35791.64, "mo": null}, "4h": {"cur": 1290.98, "wk": 143521.25, "mo": null}, "1d": {"cur": 97389.86, "wk": 962161.06, "mo": null}}}, {"c": "NFT", "tf": {"1h": {"cur": 42.62, "wk": 1011.87, "mo": null}, "4h": {"cur": 42.62, "wk": 4043.47, "mo": 2508.34}, "1d": {"cur": 11509.7, "wk": 24862.64, "mo": 14759.16}}}, {"c": "NIGHT", "tf": {"1h": {"cur": 48982.97, "wk": 50106.07, "mo": null}, "4h": {"cur": 48982.97, "wk": 200363.67, "mo": 147439.61}, "1d": {"cur": 412818.76, "wk": 1164411.61, "mo": 887364.72}}}, {"c": "NMR", "tf": {"1h": {"cur": 326.07, "wk": 2308.13, "mo": null}, "4h": {"cur": 326.07, "wk": 9227.62, "mo": 9918.03}, "1d": {"cur": 18928.47, "wk": 57376.36, "mo": 61070.25}}}, {"c": "NOT", "tf": {"1h": {"cur": 169.92, "wk": 1866.79, "mo": null}, "4h": {"cur": 169.92, "wk": 7472.46, "mo": 18552.67}, "1d": {"cur": 20004.75, "wk": 49618.55, "mo": 111280.82}}}, {"c": "OFC", "tf": {"1h": {"cur": 4594.62, "wk": 15839.84, "mo": null}, "4h": {"cur": 4594.62, "wk": 63801.47, "mo": 646824.37}, "1d": {"cur": 206003.69, "wk": 383544.11, "mo": 4172647.84}}}, {"c": "OKSOL", "tf": {"1h": {"cur": 80440.11, "wk": 8490.82, "mo": null}, "4h": {"cur": 80440.11, "wk": 34007.1, "mo": 36934.9}, "1d": {"cur": 199260.18, "wk": 198199.04, "mo": 220027.04}}}, {"c": "OL", "tf": {"1h": {"cur": 1361.66, "wk": 3270.09, "mo": null}, "4h": {"cur": 1361.66, "wk": 13112.8, "mo": 21967.81}, "1d": {"cur": 15606.75, "wk": 95733.94, "mo": 130585.81}}}, {"c": "OMI", "tf": {"1h": {"cur": 1.9, "wk": 897.23, "mo": null}, "4h": {"cur": 1.9, "wk": 3582.49, "mo": 3590.24}, "1d": {"cur": 4606.43, "wk": 22815.46, "mo": 21311.05}}}, {"c": "ONDO", "tf": {"1h": {"cur": 92647.95, "wk": 245984.31, "mo": null}, "4h": {"cur": 92647.95, "wk": 984152.37, "mo": 484482.24}, "1d": {"cur": 1357197.22, "wk": 5794718.63, "mo": 2883719.67}}}, {"c": "ONE", "tf": {"1h": {"cur": 1067.63, "wk": 2957.33, "mo": null}, "4h": {"cur": 1067.63, "wk": 11834.03, "mo": 3810.93}, "1d": {"cur": 37560.74, "wk": 65867.03, "mo": 21614.83}}}, {"c": "ONT", "tf": {"1h": {"cur": 1436.36, "wk": 2743.15, "mo": null}, "4h": {"cur": 1436.36, "wk": 10905.84, "mo": 23003.4}, "1d": {"cur": 45281.89, "wk": 63029.16, "mo": 138730.77}}}, {"c": "OP", "tf": {"1h": {"cur": 9031.49, "wk": 27999.62, "mo": null}, "4h": {"cur": 9031.49, "wk": 112057.7, "mo": 139601.43}, "1d": {"cur": 334501.22, "wk": 741793.88, "mo": 844984.22}}}, {"c": "ORBS", "tf": {"1h": {"cur": 19.88, "wk": 1132.16, "mo": null}, "4h": {"cur": 19.88, "wk": 4503.59, "mo": 5970.44}, "1d": {"cur": 29257.32, "wk": 24364.18, "mo": 35158.76}}}, {"c": "ORDI", "tf": {"1h": {"cur": 6200.79, "wk": 75661.07, "mo": null}, "4h": {"cur": 6200.79, "wk": 302393.74, "mo": 350088.64}, "1d": {"cur": 644848.25, "wk": 1834567.25, "mo": 2107968.01}}}, {"c": "PARTI", "tf": {"1h": {"cur": 1252.93, "wk": 8612.07, "mo": null}, "4h": {"cur": 1252.93, "wk": 34389.88, "mo": 49652.7}, "1d": {"cur": 141042.92, "wk": 258107.69, "mo": 288263.17}}}, {"c": "PAXG", "tf": {"1h": {"cur": 9554.49, "wk": 56422.01, "mo": null}, "4h": {"cur": 9554.49, "wk": 225625.49, "mo": 234575.02}, "1d": {"cur": 1396994.01, "wk": 1179717.52, "mo": 1362010.78}}}, {"c": "PENDLE", "tf": {"1h": {"cur": 11305.3, "wk": 8760.4, "mo": null}, "4h": {"cur": 11305.3, "wk": 35089.25, "mo": 45581.01}, "1d": {"cur": 165568.47, "wk": 202954.88, "mo": 272449.75}}}, {"c": "PENGU", "tf": {"1h": {"cur": 36571.09, "wk": 82192.76, "mo": null}, "4h": {"cur": 36571.09, "wk": 329419.2, "mo": 265767.71}, "1d": {"cur": 2082241.41, "wk": 1752127.7, "mo": 1541195.09}}}, {"c": "PEOPLE", "tf": {"1h": {"cur": 7040.03, "wk": 7506.18, "mo": null}, "4h": {"cur": 7040.03, "wk": 30083.52, "mo": 33199.53}, "1d": {"cur": 57645.49, "wk": 209817.33, "mo": 198466.76}}}, {"c": "PEPE", "tf": {"1h": {"cur": 251528.58, "wk": 266748.89, "mo": null}, "4h": {"cur": 251548.06, "wk": 1066777.55, "mo": 937276.96}, "1d": {"cur": 6196533.77, "wk": 5842871.1, "mo": 5480222.91}}}, {"c": "PHA", "tf": {"1h": {"cur": 675.09, "wk": 4665.4, "mo": null}, "4h": {"cur": 675.09, "wk": 18301.38, "mo": 13951.18}, "1d": {"cur": 43627.96, "wk": 106834.93, "mo": 83441.26}}}, {"c": "PI", "tf": {"1h": {"cur": 66973.74, "wk": 364665.13, "mo": null}, "4h": {"cur": 66137.01, "wk": 1463998.06, "mo": 746004.68}, "1d": {"cur": 5859204.76, "wk": 8648118.24, "mo": 4350080.95}}}, {"c": "PIXEL", "tf": {"1h": {"cur": 528.02, "wk": 1156.14, "mo": null}, "4h": {"cur": 528.02, "wk": 4622.8, "mo": 7804.86}, "1d": {"cur": 117683.22, "wk": 13203.42, "mo": 44077.52}}}, {"c": "PNUT", "tf": {"1h": {"cur": 8247.2, "wk": 5744.78, "mo": null}, "4h": {"cur": 8247.2, "wk": 22985.53, "mo": 34768.29}, "1d": {"cur": 119309.34, "wk": 132013.88, "mo": 206150.07}}}, {"c": "POL", "tf": {"1h": {"cur": 3781.48, "wk": 25207.84, "mo": null}, "4h": {"cur": 3781.48, "wk": 100886.08, "mo": 76287.27}, "1d": {"cur": 176603.26, "wk": 653149.93, "mo": 461047.16}}}, {"c": "POR", "tf": {"1h": {"cur": 263.91, "wk": 15090.26, "mo": null}, "4h": {"cur": 263.91, "wk": 59258.01, "mo": 21663.29}, "1d": {"cur": 56576.29, "wk": 331898.03, "mo": 123523.64}}}, {"c": "PRCL", "tf": {"1h": {"cur": 652.99, "wk": 5572.79, "mo": null}, "4h": {"cur": 699.1, "wk": 22241.61, "mo": 15925.83}, "1d": {"cur": 62490.79, "wk": 127012.42, "mo": 98603.58}}}, {"c": "PROMPT", "tf": {"1h": {"cur": 331.35, "wk": 2605.71, "mo": null}, "4h": {"cur": 331.35, "wk": 10414.96, "mo": 10436.03}, "1d": {"cur": 25180.94, "wk": 60971.4, "mo": 62348.06}}}, {"c": "PROVE", "tf": {"1h": {"cur": 3020.79, "wk": 2452.58, "mo": null}, "4h": {"cur": 3020.79, "wk": 9809.39, "mo": 19725.06}, "1d": {"cur": 24418.44, "wk": 60639.23, "mo": 123124.41}}}, {"c": "PROS", "tf": {"1h": {"cur": 13291.84, "wk": 12412.25, "mo": null}, "4h": {"cur": 13310.76, "wk": 49654.78, "mo": 102995.76}, "1d": {"cur": 347675.15, "wk": 269013.58, "mo": 596422.22}}}, {"c": "PUMP", "tf": {"1h": {"cur": 97810.92, "wk": 209962.23, "mo": null}, "4h": {"cur": 97810.92, "wk": 843778.12, "mo": 629557.54}, "1d": {"cur": 6647860.23, "wk": 4604683.52, "mo": 3587247.42}}}, {"c": "PYTH", "tf": {"1h": {"cur": 9806.51, "wk": 22788.83, "mo": null}, "4h": {"cur": 9806.51, "wk": 91150.35, "mo": 121082.04}, "1d": {"cur": 288735.3, "wk": 547880.59, "mo": 720965.49}}}, {"c": "PYUSD", "tf": {"1h": {"cur": 81.24, "wk": 2748.62, "mo": null}, "4h": {"cur": 81.24, "wk": 10995.41, "mo": 7827.68}, "1d": {"cur": 17121.05, "wk": 69421.57, "mo": 47410.21}}}, {"c": "QTUM", "tf": {"1h": {"cur": 729.64, "wk": 3304.42, "mo": null}, "4h": {"cur": 729.64, "wk": 13156.5, "mo": 8057.16}, "1d": {"cur": 56854.61, "wk": 72485.39, "mo": 47233.95}}}, {"c": "RAY", "tf": {"1h": {"cur": 22857.58, "wk": 3922.51, "mo": null}, "4h": {"cur": 22857.58, "wk": 15694.52, "mo": 28216.99}, "1d": {"cur": 111282.45, "wk": 92992.5, "mo": 171195.4}}}, {"c": "RE", "tf": {"1h": {"cur": 15373.19, "wk": 123067.11, "mo": null}, "4h": {"cur": 15373.19, "wk": 490556.73, "mo": 17428722.96}, "1d": {"cur": 1007978.96, "wk": 3069780.33, "mo": 107717206.92}}}, {"c": "RENDER", "tf": {"1h": {"cur": 11204.08, "wk": 15080.1, "mo": null}, "4h": {"cur": 11204.08, "wk": 60316.96, "mo": 69196.99}, "1d": {"cur": 192594.04, "wk": 360329.69, "mo": 414032.03}}}, {"c": "RESOLV", "tf": {"1h": {"cur": 19594.68, "wk": 22001.26, "mo": null}, "4h": {"cur": 19594.68, "wk": 87773.56, "mo": 267116.08}, "1d": {"cur": 95756.47, "wk": 532691.83, "mo": 1602028.0}}}, {"c": "RLUSD", "tf": {"1h": {"cur": 101.76, "wk": 4288.47, "mo": null}, "4h": {"cur": 101.76, "wk": 17154.6, "mo": 198046.29}, "1d": {"cur": 31353.92, "wk": 98930.27, "mo": 1189340.72}}}, {"c": "ROBO", "tf": {"1h": {"cur": 9954.16, "wk": 13856.03, "mo": null}, "4h": {"cur": 9954.16, "wk": 55505.84, "mo": 57800.81}, "1d": {"cur": 113323.56, "wk": 351422.21, "mo": 347465.85}}}, {"c": "RON", "tf": {"1h": {"cur": 292.83, "wk": 742.05, "mo": null}, "4h": {"cur": 292.83, "wk": 2960.76, "mo": 3134.45}, "1d": {"cur": 51568.35, "wk": 11658.17, "mo": 17979.77}}}, {"c": "RPL", "tf": {"1h": {"cur": 1065.9, "wk": 1138.44, "mo": null}, "4h": {"cur": 1065.9, "wk": 4535.67, "mo": 25220.89}, "1d": {"cur": 29277.86, "wk": 24070.39, "mo": 149111.2}}}, {"c": "RSR", "tf": {"1h": {"cur": 4084.45, "wk": 3532.45, "mo": null}, "4h": {"cur": 4084.45, "wk": 14133.02, "mo": 16324.85}, "1d": {"cur": 73236.62, "wk": 81477.41, "mo": 96416.1}}}, {"c": "RVN", "tf": {"1h": {"cur": 103.37, "wk": 2181.45, "mo": null}, "4h": {"cur": 103.37, "wk": 8728.74, "mo": 11025.66}, "1d": {"cur": 21680.89, "wk": 55225.95, "mo": 65105.96}}}, {"c": "S", "tf": {"1h": {"cur": 5952.2, "wk": 2138.21, "mo": null}, "4h": {"cur": 5952.2, "wk": 8559.5, "mo": 63615.9}, "1d": {"cur": 43212.92, "wk": 54458.09, "mo": 380654.14}}}, {"c": "SAFE", "tf": {"1h": {"cur": 341.15, "wk": 5412.38, "mo": null}, "4h": {"cur": 341.15, "wk": 21624.1, "mo": 40301.25}, "1d": {"cur": 58387.64, "wk": 140111.93, "mo": 240894.17}}}, {"c": "SAHARA", "tf": {"1h": {"cur": 2253.88, "wk": 3657.01, "mo": null}, "4h": {"cur": 2253.88, "wk": 14611.76, "mo": 37220.51}, "1d": {"cur": 50066.64, "wk": 90474.29, "mo": 224013.69}}}, {"c": "SAND", "tf": {"1h": {"cur": 1549.56, "wk": 4199.35, "mo": null}, "4h": {"cur": 1549.56, "wk": 16819.39, "mo": 41028.09}, "1d": {"cur": 61293.27, "wk": 98657.42, "mo": 290927.51}}}, {"c": "SATS", "tf": {"1h": {"cur": 1765.82, "wk": 5796.06, "mo": null}, "4h": {"cur": 1770.05, "wk": 23209.71, "mo": 44128.59}, "1d": {"cur": 63135.86, "wk": 149232.37, "mo": 268372.4}}}, {"c": "SCR", "tf": {"1h": {"cur": 378.07, "wk": 1448.16, "mo": null}, "4h": {"cur": 378.07, "wk": 5782.49, "mo": 7487.0}, "1d": {"cur": 12939.87, "wk": 34382.99, "mo": 44950.24}}}, {"c": "SD", "tf": {"1h": {"cur": 1778.49, "wk": 1102.32, "mo": null}, "4h": {"cur": 1778.49, "wk": 4408.79, "mo": 16565.75}, "1d": {"cur": 18379.47, "wk": 25282.5, "mo": 93374.98}}}, {"c": "SEI", "tf": {"1h": {"cur": 9824.07, "wk": 10692.65, "mo": null}, "4h": {"cur": 9824.07, "wk": 42750.76, "mo": 100154.46}, "1d": {"cur": 252139.19, "wk": 242154.46, "mo": 605121.68}}}, {"c": "SENT", "tf": {"1h": {"cur": 37858.35, "wk": 36388.08, "mo": null}, "4h": {"cur": 37858.35, "wk": 144784.65, "mo": 77390.83}, "1d": {"cur": 339396.62, "wk": 841315.77, "mo": 451896.96}}}, {"c": "SHIB", "tf": {"1h": {"cur": 16983.39, "wk": 38876.57, "mo": null}, "4h": {"cur": 16921.14, "wk": 155679.81, "mo": 170719.42}, "1d": {"cur": 733564.45, "wk": 884504.59, "mo": 1009545.76}}}, {"c": "SKL", "tf": {"1h": {"cur": 7625.57, "wk": 15777.47, "mo": null}, "4h": {"cur": 7625.57, "wk": 63035.87, "mo": 53284.71}, "1d": {"cur": 83917.87, "wk": 377842.08, "mo": 296754.9}}}, {"c": "SKY", "tf": {"1h": {"cur": 10749.72, "wk": 24079.62, "mo": null}, "4h": {"cur": 10749.72, "wk": 96291.46, "mo": 78503.26}, "1d": {"cur": 193749.6, "wk": 595837.52, "mo": 467108.82}}}, {"c": "SLP", "tf": {"1h": {"cur": 0.0, "wk": 428.69, "mo": null}, "4h": {"cur": 0.0, "wk": 1719.26, "mo": 5794.18}, "1d": {"cur": 33295.13, "wk": 5712.63, "mo": 35420.96}}}, {"c": "SLX", "tf": {"1h": {"cur": 21569.38, "wk": 142285.22, "mo": null}, "4h": {"cur": 21569.38, "wk": 566086.55, "mo": null}, "1d": {"cur": 693575.56, "wk": 3542739.04, "mo": null}}}, {"c": "SNT", "tf": {"1h": {"cur": 355.1, "wk": 1027.58, "mo": null}, "4h": {"cur": 355.1, "wk": 4102.75, "mo": 12052.21}, "1d": {"cur": 9110.16, "wk": 27416.08, "mo": 72318.42}}}, {"c": "SNX", "tf": {"1h": {"cur": 15949.8, "wk": 8210.58, "mo": null}, "4h": {"cur": 15949.8, "wk": 32829.49, "mo": 38120.89}, "1d": {"cur": 251282.99, "wk": 202633.64, "mo": 223658.1}}}, {"c": "SONIC", "tf": {"1h": {"cur": 80.24, "wk": 543.82, "mo": null}, "4h": {"cur": 80.24, "wk": 2173.47, "mo": 3186.13}, "1d": {"cur": 5801.55, "wk": 12904.34, "mo": 19263.91}}}, {"c": "SOPH", "tf": {"1h": {"cur": 196.62, "wk": 551.18, "mo": null}, "4h": {"cur": 196.62, "wk": 2205.71, "mo": 4864.04}, "1d": {"cur": 8147.1, "wk": 12948.28, "mo": 28791.97}}}, {"c": "SPACE", "tf": {"1h": {"cur": 3803.04, "wk": 15822.09, "mo": null}, "4h": {"cur": 3803.04, "wk": 63295.71, "mo": 93884.43}, "1d": {"cur": 203063.09, "wk": 372837.58, "mo": 570486.64}}}, {"c": "SPK", "tf": {"1h": {"cur": 3286.61, "wk": 10558.01, "mo": null}, "4h": {"cur": 3286.61, "wk": 42287.39, "mo": 45621.9}, "1d": {"cur": 258783.31, "wk": 232471.44, "mo": 266927.71}}}, {"c": "SPURS", "tf": {"1h": {"cur": 27.08, "wk": 462.75, "mo": null}, "4h": {"cur": 27.08, "wk": 1842.94, "mo": 5299.84}, "1d": {"cur": 863.29, "wk": 11235.33, "mo": 29050.86}}}, {"c": "SSV", "tf": {"1h": {"cur": 366.08, "wk": 3128.8, "mo": null}, "4h": {"cur": 366.08, "wk": 12515.3, "mo": 19383.59}, "1d": {"cur": 47195.04, "wk": 76239.08, "mo": 116830.93}}}, {"c": "STETH", "tf": {"1h": {"cur": 5119.84, "wk": 10207.65, "mo": null}, "4h": {"cur": 5119.84, "wk": 40907.51, "mo": 50782.66}, "1d": {"cur": 158593.52, "wk": 253192.18, "mo": 301409.89}}}, {"c": "STORJ", "tf": {"1h": {"cur": 141.46, "wk": 168.8, "mo": null}, "4h": {"cur": 141.46, "wk": 676.88, "mo": 3088.96}, "1d": {"cur": 690.61, "wk": 5057.55, "mo": 18492.29}}}, {"c": "STRK", "tf": {"1h": {"cur": 8464.91, "wk": 35858.71, "mo": null}, "4h": {"cur": 8464.91, "wk": 143481.99, "mo": 160779.03}, "1d": {"cur": 290882.11, "wk": 856808.37, "mo": 960237.09}}}, {"c": "STX", "tf": {"1h": {"cur": 1638.6, "wk": 5424.33, "mo": null}, "4h": {"cur": 1638.6, "wk": 21694.55, "mo": 26515.77}, "1d": {"cur": 51032.92, "wk": 156937.45, "mo": 159610.16}}}, {"c": "SUSHI", "tf": {"1h": {"cur": 3965.56, "wk": 8395.03, "mo": null}, "4h": {"cur": 3965.56, "wk": 33618.38, "mo": 25380.04}, "1d": {"cur": 158828.02, "wk": 180610.81, "mo": 148336.14}}}, {"c": "SWFTC", "tf": {"1h": {"cur": 217.26, "wk": 712.93, "mo": null}, "4h": {"cur": 217.26, "wk": 2851.08, "mo": 3600.71}, "1d": {"cur": 8856.77, "wk": 16982.49, "mo": 21569.99}}}, {"c": "T", "tf": {"1h": {"cur": 126.65, "wk": 7132.06, "mo": null}, "4h": {"cur": 126.65, "wk": 28052.11, "mo": 23107.32}, "1d": {"cur": 10315.58, "wk": 190165.29, "mo": 135656.63}}}, {"c": "TAO", "tf": {"1h": {"cur": 5326.79, "wk": 52083.27, "mo": null}, "4h": {"cur": 5326.79, "wk": 208374.68, "mo": null}, "1d": {"cur": 324470.23, "wk": 7091976.88, "mo": null}}}, {"c": "THETA", "tf": {"1h": {"cur": 1402.48, "wk": 2805.35, "mo": null}, "4h": {"cur": 1402.48, "wk": 11212.45, "mo": 20666.09}, "1d": {"cur": 17861.0, "wk": 75026.92, "mo": 124047.69}}}, {"c": "TIA", "tf": {"1h": {"cur": 15111.42, "wk": 30138.1, "mo": null}, "4h": {"cur": 15111.42, "wk": 120267.74, "mo": 159657.38}, "1d": {"cur": 352180.74, "wk": 737770.98, "mo": 950283.85}}}, {"c": "TNSR", "tf": {"1h": {"cur": 2368.52, "wk": 3904.17, "mo": null}, "4h": {"cur": 2368.52, "wk": 15635.0, "mo": 111616.27}, "1d": {"cur": 43708.15, "wk": 107615.25, "mo": 644855.01}}}, {"c": "GRAM", "tf": {"1h": {"cur": 42226.82, "wk": 124617.35, "mo": null}, "4h": {"cur": 42226.82, "wk": 499919.45, "mo": 706810.91}, "1d": {"cur": 1490894.5, "wk": 2947140.22, "mo": 4206582.77}}}, {"c": "TOSHI", "tf": {"1h": {"cur": 5182.85, "wk": 11424.23, "mo": null}, "4h": {"cur": 5182.85, "wk": 45849.67, "mo": 29662.98}, "1d": {"cur": 80179.02, "wk": 258894.35, "mo": 173731.18}}}, {"c": "TRA", "tf": {"1h": {"cur": 0.0, "wk": 892.51, "mo": null}, "4h": {"cur": 0.0, "wk": 3539.37, "mo": 1855.19}, "1d": {"cur": 1212.41, "wk": 22014.13, "mo": 11188.63}}}, {"c": "TRB", "tf": {"1h": {"cur": 1680.31, "wk": 10548.43, "mo": null}, "4h": {"cur": 1680.31, "wk": 42216.46, "mo": 88985.98}, "1d": {"cur": 126310.6, "wk": 252737.31, "mo": 531339.56}}}, {"c": "TRUMP", "tf": {"1h": {"cur": 33037.46, "wk": 177378.09, "mo": null}, "4h": {"cur": 33037.46, "wk": 710779.74, "mo": 624226.23}, "1d": {"cur": 2466810.22, "wk": 4016102.18, "mo": 3684322.6}}}, {"c": "TRX", "tf": {"1h": {"cur": 114999.47, "wk": 236528.96, "mo": null}, "4h": {"cur": 114999.47, "wk": 946238.34, "mo": 1249177.03}, "1d": {"cur": 1929703.83, "wk": 5870065.34, "mo": 7582570.2}}}, {"c": "TURBO", "tf": {"1h": {"cur": 1635.33, "wk": 3275.79, "mo": null}, "4h": {"cur": 1635.33, "wk": 13091.72, "mo": 21198.97}, "1d": {"cur": 30057.73, "wk": 77470.92, "mo": 126032.29}}}, {"c": "UMA", "tf": {"1h": {"cur": 577.59, "wk": 1382.34, "mo": null}, "4h": {"cur": 577.59, "wk": 5522.67, "mo": 5637.41}, "1d": {"cur": 9591.63, "wk": 33026.91, "mo": 33626.38}}}, {"c": "UNI", "tf": {"1h": {"cur": 147933.25, "wk": 157178.89, "mo": null}, "4h": {"cur": 147933.25, "wk": 628490.94, "mo": 712797.8}, "1d": {"cur": 2083189.97, "wk": 3798931.96, "mo": 4267595.19}}}, {"c": "USAT", "tf": {"1h": {"cur": 0.0, "wk": 4669.97, "mo": null}, "4h": {"cur": 0.0, "wk": 18677.92, "mo": 5945.84}, "1d": {"cur": 3752.7, "wk": 112968.25, "mo": 35542.08}}}, {"c": "USDG", "tf": {"1h": {"cur": 5988.07, "wk": 241110.14, "mo": null}, "4h": {"cur": 5988.07, "wk": 964440.58, "mo": 1895760.55}, "1d": {"cur": 3185202.33, "wk": 5749051.74, "mo": 11641676.48}}}, {"c": "USD1", "tf": {"1h": {"cur": 0.0, "wk": 4185.93, "mo": null}, "4h": {"cur": 0.0, "wk": 16743.16, "mo": 39278.39}, "1d": {"cur": 503.0, "wk": 107303.85, "mo": 237064.61}}}, {"c": "USDS", "tf": {"1h": {"cur": 0.0, "wk": 585.12, "mo": null}, "4h": {"cur": 0.0, "wk": 2340.41, "mo": 8906.85}, "1d": {"cur": 20130.31, "wk": 11218.11, "mo": 52788.0}}}, {"c": "VELO", "tf": {"1h": {"cur": 24.29, "wk": 2390.26, "mo": null}, "4h": {"cur": 24.29, "wk": 9619.43, "mo": 6916.95}, "1d": {"cur": 21270.44, "wk": 56362.13, "mo": 41292.99}}}, {"c": "VELODROME", "tf": {"1h": {"cur": 289.05, "wk": 621.79, "mo": null}, "4h": {"cur": 289.05, "wk": 2484.61, "mo": 8342.72}, "1d": {"cur": 4109.53, "wk": 15168.51, "mo": 51632.06}}}, {"c": "VINE", "tf": {"1h": {"cur": 0.0, "wk": 2040.02, "mo": null}, "4h": {"cur": 0.0, "wk": 8167.34, "mo": 30432.56}, "1d": {"cur": 11477.88, "wk": 53017.49, "mo": 187168.03}}}, {"c": "VIRTUAL", "tf": {"1h": {"cur": 24358.55, "wk": 57622.3, "mo": null}, "4h": {"cur": 24358.55, "wk": 230735.46, "mo": 164469.64}, "1d": {"cur": 709716.63, "wk": 1346106.09, "mo": 964345.44}}}, {"c": "W", "tf": {"1h": {"cur": 1849.84, "wk": 10059.13, "mo": null}, "4h": {"cur": 1849.84, "wk": 40270.67, "mo": 100633.88}, "1d": {"cur": 243785.65, "wk": 228072.26, "mo": 604583.81}}}, {"c": "WAXP", "tf": {"1h": {"cur": 398.31, "wk": 363.01, "mo": null}, "4h": {"cur": 398.31, "wk": 1452.59, "mo": 6145.08}, "1d": {"cur": 4323.19, "wk": 9591.0, "mo": 37114.3}}}, {"c": "WCT", "tf": {"1h": {"cur": 782.12, "wk": 2454.13, "mo": null}, "4h": {"cur": 782.12, "wk": 9814.18, "mo": 32837.56}, "1d": {"cur": 57481.59, "wk": 65642.99, "mo": 210188.22}}}, {"c": "WET", "tf": {"1h": {"cur": 1333.81, "wk": 12729.11, "mo": null}, "4h": {"cur": 1333.81, "wk": 50901.4, "mo": 67274.52}, "1d": {"cur": 154292.84, "wk": 293221.32, "mo": 397488.38}}}, {"c": "WIF", "tf": {"1h": {"cur": 62615.49, "wk": 17378.46, "mo": null}, "4h": {"cur": 61715.09, "wk": 69465.61, "mo": 101584.73}, "1d": {"cur": 389066.4, "wk": 403802.15, "mo": 597341.56}}}, {"c": "WIN", "tf": {"1h": {"cur": 222.95, "wk": 3035.76, "mo": null}, "4h": {"cur": 222.95, "wk": 12138.1, "mo": 6250.66}, "1d": {"cur": 9214.68, "wk": 75129.78, "mo": 37343.14}}}, {"c": "WLD", "tf": {"1h": {"cur": 71757.88, "wk": 242532.83, "mo": null}, "4h": {"cur": 71757.88, "wk": 969992.68, "mo": 1637195.61}, "1d": {"cur": 2463708.53, "wk": 6188742.79, "mo": 9889679.32}}}, {"c": "WLFI", "tf": {"1h": {"cur": 63459.75, "wk": 44835.43, "mo": null}, "4h": {"cur": 63459.75, "wk": 179372.56, "mo": 199520.78}, "1d": {"cur": 712811.05, "wk": 1050510.91, "mo": 1188511.94}}}, {"c": "WOO", "tf": {"1h": {"cur": 267.22, "wk": 3114.34, "mo": null}, "4h": {"cur": 267.22, "wk": 12452.05, "mo": 7265.67}, "1d": {"cur": 10493.84, "wk": 74348.19, "mo": 43618.15}}}, {"c": "XAUT", "tf": {"1h": {"cur": 207897.05, "wk": 255540.71, "mo": null}, "4h": {"cur": 207897.05, "wk": 1022455.33, "mo": 1031922.96}, "1d": {"cur": 2692746.87, "wk": 6105033.97, "mo": 6157775.95}}}, {"c": "XCH", "tf": {"1h": {"cur": 3345.89, "wk": 5951.82, "mo": null}, "4h": {"cur": 3345.89, "wk": 23765.0, "mo": 26978.54}, "1d": {"cur": 106489.19, "wk": 132018.45, "mo": 159515.92}}}, {"c": "XLM", "tf": {"1h": {"cur": 32585.55, "wk": 101845.74, "mo": null}, "4h": {"cur": 32585.55, "wk": 406783.23, "mo": 607470.7}, "1d": {"cur": 957828.94, "wk": 2449311.53, "mo": 3685982.83}}}, {"c": "XPL", "tf": {"1h": {"cur": 21832.29, "wk": 90368.47, "mo": null}, "4h": {"cur": 21832.29, "wk": 360474.7, "mo": 598194.23}, "1d": {"cur": 1039980.54, "wk": 2177474.88, "mo": 3603504.2}}}, {"c": "XTZ", "tf": {"1h": {"cur": 713.61, "wk": 4564.43, "mo": null}, "4h": {"cur": 713.61, "wk": 18254.9, "mo": 19807.67}, "1d": {"cur": 49212.92, "wk": 105347.46, "mo": 117685.0}}}, {"c": "YB", "tf": {"1h": {"cur": 2972.26, "wk": 11042.95, "mo": null}, "4h": {"cur": 2972.26, "wk": 44530.85, "mo": 16144.36}, "1d": {"cur": 566899.64, "wk": 182056.5, "mo": 76700.05}}}, {"c": "YFI", "tf": {"1h": {"cur": 593.73, "wk": 5142.75, "mo": null}, "4h": {"cur": 593.73, "wk": 20544.9, "mo": 46834.83}, "1d": {"cur": 31101.79, "wk": 126374.54, "mo": 285147.03}}}, {"c": "YGG", "tf": {"1h": {"cur": 8797.18, "wk": 5899.29, "mo": null}, "4h": {"cur": 8797.18, "wk": 23539.81, "mo": 23992.98}, "1d": {"cur": 226878.91, "wk": 119464.65, "mo": 143263.29}}}, {"c": "ZAMA", "tf": {"1h": {"cur": 126759.46, "wk": 14109.81, "mo": null}, "4h": {"cur": 126800.58, "wk": 56706.35, "mo": 92329.68}, "1d": {"cur": 603849.93, "wk": 321095.37, "mo": 547217.18}}}, {"c": "ZBCN", "tf": {"1h": {"cur": 6992.49, "wk": 12896.06, "mo": null}, "4h": {"cur": 7009.41, "wk": 51566.32, "mo": 39842.56}, "1d": {"cur": 254288.94, "wk": 280505.84, "mo": 231510.57}}}, {"c": "ZENT", "tf": {"1h": {"cur": 362.91, "wk": 933.81, "mo": null}, "4h": {"cur": 362.91, "wk": 3732.04, "mo": 6510.6}, "1d": {"cur": 11540.24, "wk": 23447.09, "mo": 38986.91}}}, {"c": "ZEN", "tf": {"1h": {"cur": 3365.35, "wk": 5775.11, "mo": null}, "4h": {"cur": 3365.35, "wk": 23110.1, "mo": 22847.46}, "1d": {"cur": 70078.6, "wk": 142290.92, "mo": 138717.24}}}, {"c": "ZETA", "tf": {"1h": {"cur": 520.93, "wk": 1985.98, "mo": null}, "4h": {"cur": 520.93, "wk": 7947.96, "mo": 11053.79}, "1d": {"cur": 23960.71, "wk": 53221.61, "mo": 66631.33}}}, {"c": "ZEUS", "tf": {"1h": {"cur": 175.36, "wk": 3159.22, "mo": null}, "4h": {"cur": 175.36, "wk": 12525.76, "mo": 22038.11}, "1d": {"cur": 10130.98, "wk": 80220.57, "mo": 128235.05}}}, {"c": "ZIL", "tf": {"1h": {"cur": 3196.13, "wk": 5600.07, "mo": null}, "4h": {"cur": 3196.13, "wk": 22444.57, "mo": 26262.97}, "1d": {"cur": 266677.11, "wk": 106678.15, "mo": 150325.84}}}, {"c": "ZK", "tf": {"1h": {"cur": 17696.93, "wk": 7024.57, "mo": null}, "4h": {"cur": 17696.93, "wk": 28070.67, "mo": 35820.25}, "1d": {"cur": 149840.9, "wk": 166581.07, "mo": 214399.58}}}, {"c": "ZKJ", "tf": {"1h": {"cur": 211.58, "wk": 2981.08, "mo": null}, "4h": {"cur": 211.58, "wk": 11906.27, "mo": 23411.93}, "1d": {"cur": 51268.83, "wk": 81871.15, "mo": 152463.14}}}, {"c": "ZORA", "tf": {"1h": {"cur": 3592.95, "wk": 6894.35, "mo": null}, "4h": {"cur": 3592.95, "wk": 27391.26, "mo": 12410.42}, "1d": {"cur": 61804.27, "wk": 157244.22, "mo": 72797.55}}}, {"c": "ZRO", "tf": {"1h": {"cur": 14107.32, "wk": 29525.96, "mo": null}, "4h": {"cur": 14107.32, "wk": 117848.1, "mo": 141643.58}, "1d": {"cur": 399175.68, "wk": 678885.86, "mo": 845232.06}}}, {"c": "ZRX", "tf": {"1h": {"cur": 108.98, "wk": 460.16, "mo": null}, "4h": {"cur": 108.98, "wk": 1841.83, "mo": 3687.11}, "1d": {"cur": 10066.04, "wk": 10095.9, "mo": 22206.31}}}]}